
<annotation>
    <folder>images</folder>
    <filename>maksssksksss697.png</filename>
    <size>
        <width>400</width>
        <height>300</height>
        <depth>3</depth>
    </size>
    <segmented>0</segmented>
    <object>
        <name>with_mask</name>
        <pose>Unspecified</pose>
        <truncated>0</truncated>
        <occluded>0</occluded>
        <difficult>0</difficult>
        <bndbox>
            <xmin>39</xmin>
            <ymin>83</ymin>
            <xmax>149</xmax>
            <ymax>216</ymax>
        </bndbox>
    </object>
    <object>
        <name>with_mask</name>
        <pose>Unspecified</pose>
        <truncated>0</truncated>
        <occluded>0</occluded>
        <difficult>0</difficult>
        <bndbox>
            <xmin>239</xmin>
            <ymin>95</ymin>
            <xmax>368</xmax>
            <ymax>235</ymax>
        </bndbox>
    </object>
</annotation>