
<annotation>
    <folder>images</folder>
    <filename>maksssksksss329.png</filename>
    <size>
        <width>400</width>
        <height>267</height>
        <depth>3</depth>
    </size>
    <segmented>0</segmented>
    <object>
        <name>with_mask</name>
        <pose>Unspecified</pose>
        <truncated>0</truncated>
        <occluded>0</occluded>
        <difficult>0</difficult>
        <bndbox>
            <xmin>44</xmin>
            <ymin>25</ymin>
            <xmax>95</xmax>
            <ymax>81</ymax>
        </bndbox>
    </object>
    <object>
        <name>with_mask</name>
        <pose>Unspecified</pose>
        <truncated>0</truncated>
        <occluded>0</occluded>
        <difficult>0</difficult>
        <bndbox>
            <xmin>50</xmin>
            <ymin>121</ymin>
            <xmax>89</xmax>
            <ymax>158</ymax>
        </bndbox>
    </object>
    <object>
        <name>with_mask</name>
        <pose>Unspecified</pose>
        <truncated>0</truncated>
        <occluded>0</occluded>
        <difficult>0</difficult>
        <bndbox>
            <xmin>41</xmin>
            <ymin>210</ymin>
            <xmax>88</xmax>
            <ymax>260</ymax>
        </bndbox>
    </object>
    <object>
        <name>with_mask</name>
        <pose>Unspecified</pose>
        <truncated>0</truncated>
        <occluded>0</occluded>
        <difficult>0</difficult>
        <bndbox>
            <xmin>176</xmin>
            <ymin>29</ymin>
            <xmax>228</xmax>
            <ymax>85</ymax>
        </bndbox>
    </object>
    <object>
        <name>with_mask</name>
        <pose>Unspecified</pose>
        <truncated>0</truncated>
        <occluded>0</occluded>
        <difficult>0</difficult>
        <bndbox>
            <xmin>175</xmin>
            <ymin>123</ymin>
            <xmax>225</xmax>
            <ymax>169</ymax>
        </bndbox>
    </object>
    <object>
        <name>with_mask</name>
        <pose>Unspecified</pose>
        <truncated>0</truncated>
        <occluded>0</occluded>
        <difficult>0</difficult>
        <bndbox>
            <xmin>177</xmin>
            <ymin>212</ymin>
            <xmax>227</xmax>
            <ymax>259</ymax>
        </bndbox>
    </object>
    <object>
        <name>with_mask</name>
        <pose>Unspecified</pose>
        <truncated>0</truncated>
        <occluded>0</occluded>
        <difficult>0</difficult>
        <bndbox>
            <xmin>312</xmin>
            <ymin>28</ymin>
            <xmax>360</xmax>
            <ymax>81</ymax>
        </bndbox>
    </object>
    <object>
        <name>with_mask</name>
        <pose>Unspecified</pose>
        <truncated>0</truncated>
        <occluded>0</occluded>
        <difficult>0</difficult>
        <bndbox>
            <xmin>302</xmin>
            <ymin>118</ymin>
            <xmax>346</xmax>
            <ymax>169</ymax>
        </bndbox>
    </object>
    <object>
        <name>with_mask</name>
        <pose>Unspecified</pose>
        <truncated>0</truncated>
        <occluded>0</occluded>
        <difficult>0</difficult>
        <bndbox>
            <xmin>288</xmin>
            <ymin>182</ymin>
            <xmax>368</xmax>
            <ymax>264</ymax>
        </bndbox>
    </object>
</annotation>