
<annotation>
    <folder>images</folder>
    <filename>maksssksksss337.png</filename>
    <size>
        <width>246</width>
        <height>400</height>
        <depth>3</depth>
    </size>
    <segmented>0</segmented>
    <object>
        <name>with_mask</name>
        <pose>Unspecified</pose>
        <truncated>0</truncated>
        <occluded>0</occluded>
        <difficult>0</difficult>
        <bndbox>
            <xmin>115</xmin>
            <ymin>32</ymin>
            <xmax>145</xmax>
            <ymax>70</ymax>
        </bndbox>
    </object>
</annotation>